COPYING
MANIFEST.in
README.md
setup.py
alba/__init__.py
alba/mistral/__init__.py
alba/mistral/image.py
alba/mistral/magnifylib.py
alba/mistral/mosaicnex.py
alba/mistral/mosaicnorm.py
alba/mistral/parser.py
alba/mistral/specnorm.py
alba/mistral/stack_operate.py
alba/mistral/tomonorm.py
alba/mistral/txrmnex.py
alba/mistral/util.py
alba/mistral/xrm2hdf5.py
alba/mistral/xrmnex.py
alba/mistral/images/__init__.py
alba/mistral/images/imagestostack.py
alba/mistral/images/multiplealign.py
alba/mistral/images/multipleaverage.py
alba/mistral/images/multiplecrop.py
alba/mistral/images/multiplenormalization.py
alba/mistral/images/multiplexrm2h5.py
alba/mistral/images/util.py
alba/mistral/scripts/__init__.py
alba/mistral/scripts/automosaic2nexus.py
alba/mistral/scripts/autonormalize.py
alba/mistral/scripts/autotxrm2nexus.py
alba/mistral/scripts/copy2proc.py
alba/mistral/scripts/ctbio.py
alba/mistral/scripts/ctbiopartial.py
alba/mistral/scripts/energyscan.py
alba/mistral/scripts/image_operate.py
alba/mistral/scripts/img2stack.py
alba/mistral/scripts/magnetism.py
alba/mistral/scripts/magnify.py
alba/mistral/scripts/manyalign.py
alba/mistral/scripts/manyaverage.py
alba/mistral/scripts/manycrop.py
alba/mistral/scripts/manynorm.py
alba/mistral/scripts/manytomos2nexus.py
alba/mistral/scripts/manyxrm2h5.py
alba/mistral/scripts/manyxrm2norm.py
alba/mistral/scripts/mosaic2nexus.py
alba/mistral/scripts/normalize.py
alba/mistral/scripts/txrm2nexus.py
alba/mistral/scripts/xrm2h5.py
alba/mistral/scripts/xrm2nexus.py
alba/mistral/scripts/xtendof.py
alba_mistral.egg-info/PKG-INFO
alba_mistral.egg-info/SOURCES.txt
alba_mistral.egg-info/dependency_links.txt
alba_mistral.egg-info/entry_points.txt
alba_mistral.egg-info/requires.txt
alba_mistral.egg-info/top_level.txt
test/__init__.py
test/test_txrmnex.py
test/test_workflow.py